basi/__init__.py
basi/_common/__init__.py
basi/_common/lookups.py
basi/apps.py
basi/base.py
basi/canvas.py
basi/django/__init__.py
basi/django/_persistent_models.py
basi/management/__init__.py
basi/management/commands/__init__.py
basi/management/commands/celery.py
basi/management/commands/runworker.py
basi/serializers/__init__.py
basi/serializers/persistent_pickle.py
basi/testing/__init__.py
basi/testing/tasks.py
basi-0.6.3.dist-info/METADATA
basi-0.6.3.dist-info/WHEEL
basi-0.6.3.dist-info/LICENSE.txt
basi-0.6.3.dist-info/RECORD
