Metadata-Version: 2.1
Name: basi
Version: 0.6.3
Summary: Distributed tasks and signals
Home-page: https://github.com/davidkyalo/basi
License: MIT
Keywords: Celery
Author: David Kyalo
Author-email: davidmkyalo@gmail.com
Requires-Python: >=3.9,<4.0
Classifier: License :: OSI Approved :: MIT License
Classifier: Programming Language :: Python :: 3
Classifier: Programming Language :: Python :: 3.9
Classifier: Programming Language :: Python :: 3.10
Classifier: Programming Language :: Python :: 3.11
Classifier: Programming Language :: Python :: 3.10
Classifier: Programming Language :: Python :: 3.9
Requires-Dist: Django
Requires-Dist: attrs (>=21.4.0)
Requires-Dist: blinker (>=1.4,<2.0)
Requires-Dist: celery (>=5.2.7,<6.0.0)
Requires-Dist: celery-types (>=0.14.0,<0.15.0)
Requires-Dist: typing-extensions (>=4.1.1,<5.0.0)
Project-URL: Documentation, https://davidkyalo.github.io/basi
Project-URL: Repository, https://github.com/davidkyalo/basi
